README.md
setup.cfg
setup.py
torchfit/__init__.py
torchfit/learner.py
torchfit/lr_finder.py
torchfit/utils.py
torchfit/version.py
torchfit.egg-info/PKG-INFO
torchfit.egg-info/SOURCES.txt
torchfit.egg-info/dependency_links.txt
torchfit.egg-info/requires.txt
torchfit.egg-info/top_level.txt