Metadata-Version: 2.1
Name: torchfit
Version: 0.2.2
Summary: TorchFit is a simple, easy-to-use, and minimalistic training-helper for PyTorch
Home-page: https://github.com/amaiya/torchfit
Author: Arun S. Maiya
Author-email: arun@maiya.net
License: MIT
Keywords: pytorch,deep learning,machine learning
Platform: UNKNOWN
Classifier: Development Status :: 4 - Beta
Classifier: Intended Audience :: Developers
Classifier: Topic :: Scientific/Engineering :: Artificial Intelligence
Classifier: License :: OSI Approved :: MIT License
Classifier: Programming Language :: Python :: 3.6
Classifier: Programming Language :: Python :: 3.7
